[
  {
    "timestamp": "2024-04-20T14:00:00Z",
    "odds": {
      "timestamp": "2024-04-20T13:55:39Z",
      "previous_timestamp": "2024-04-20T13:50:40Z",
      "next_timestamp": "2024-04-20T14:00:41Z",
      "data": {
        "id": "a55f9238ff1d9711f6c35ab6d69cede0",
        "sport_key": "cricket_ipl",
        "sport_title": "IPL",
        "commence_time": "2024-04-20T14:00:00Z",
        "home_team": "Delhi Capitals",
        "away_team": "Sunrisers Hyderabad",
        "bookmakers": [
          {
            "key": "fanduel",
            "title": "FanDuel",
            "last_update": "2024-04-20T13:55:13Z",
            "markets": [
              {
                "key": "h2h",
                "last_update": "2024-04-20T13:55:13Z",
                "outcomes": [
                  {
                    "name": "Delhi Capitals",
                    "price": 2.2
                  },
                  {
                    "name": "Sunrisers Hyderabad",
                    "price": 1.69
                  }
                ]
              }
            ]
          }
        ]
      }
    }
  },
  {
    "timestamp": "2024-04-20T14:05:00Z",
    "odds": {
      "timestamp": "2024-04-20T14:00:41Z",
      "previous_timestamp": "2024-04-20T13:55:39Z",
      "next_timestamp": "2024-04-20T14:05:39Z",
      "data": {
        "id": "a55f9238ff1d9711f6c35ab6d69cede0",
        "sport_key": "cricket_ipl",
        "sport_title": "IPL",
        "commence_time": "2024-04-20T14:00:00Z",
        "home_team": "Delhi Capitals",
        "away_team": "Sunrisers Hyderabad",
        "bookmakers": [
          {
            "key": "fanduel",
            "title": "FanDuel",
            "last_update": "2024-04-20T14:00:07Z",
            "markets": [
              {
                "key": "h2h",
                "last_update": "2024-04-20T14:00:07Z",
                "outcomes": [
                  {
                    "name": "Delhi Capitals",
                    "price": 2.15
                  },
                  {
                    "name": "Sunrisers Hyderabad",
                    "price": 1.71
                  }
                ]
              }
            ]
          }
        ]
      }
    }
  },
  {
    "timestamp": "2024-04-20T14:10:00Z",
    "odds": {
      "timestamp": "2024-04-20T14:05:39Z",
      "previous_timestamp": "2024-04-20T14:00:41Z",
      "next_timestamp": "2024-04-20T14:10:38Z",
      "data": {
        "id": "a55f9238ff1d9711f6c35ab6d69cede0",
        "sport_key": "cricket_ipl",
        "sport_title": "IPL",
        "commence_time": "2024-04-20T14:00:00Z",
        "home_team": "Delhi Capitals",
        "away_team": "Sunrisers Hyderabad",
        "bookmakers": [
          {
            "key": "fanduel",
            "title": "FanDuel",
            "last_update": "2024-04-20T14:04:57Z",
            "markets": [
              {
                "key": "h2h",
                "last_update": "2024-04-20T14:04:57Z",
                "outcomes": [
                  {
                    "name": "Delhi Capitals",
                    "price": 2.7
                  },
                  {
                    "name": "Sunrisers Hyderabad",
                    "price": 1.48
                  }
                ]
              }
            ]
          }
        ]
      }
    }
  },
  {
    "timestamp": "2024-04-20T14:15:00Z",
    "odds": {
      "timestamp": "2024-04-20T14:10:38Z",
      "previous_timestamp": "2024-04-20T14:05:39Z",
      "next_timestamp": "2024-04-20T14:15:39Z",
      "data": {
        "id": "a55f9238ff1d9711f6c35ab6d69cede0",
        "sport_key": "cricket_ipl",
        "sport_title": "IPL",
        "commence_time": "2024-04-20T14:00:00Z",
        "home_team": "Delhi Capitals",
        "away_team": "Sunrisers Hyderabad",
        "bookmakers": [
          {
            "key": "fanduel",
            "title": "FanDuel",
            "last_update": "2024-04-20T14:09:43Z",
            "markets": [
              {
                "key": "h2h",
                "last_update": "2024-04-20T14:09:43Z",
                "outcomes": [
                  {
                    "name": "Delhi Capitals",
                    "price": 3.5
                  },
                  {
                    "name": "Sunrisers Hyderabad",
                    "price": 1.31
                  }
                ]
              }
            ]
          }
        ]
      }
    }
  },
  {
    "timestamp": "2024-04-20T14:20:00Z",
    "odds": {
      "timestamp": "2024-04-20T14:15:39Z",
      "previous_timestamp": "2024-04-20T14:10:38Z",
      "next_timestamp": "2024-04-20T14:20:38Z",
      "data": {
        "id": "a55f9238ff1d9711f6c35ab6d69cede0",
        "sport_key": "cricket_ipl",
        "sport_title": "IPL",
        "commence_time": "2024-04-20T14:00:00Z",
        "home_team": "Delhi Capitals",
        "away_team": "Sunrisers Hyderabad",
        "bookmakers": [
          {
            "key": "fanduel",
            "title": "FanDuel",
            "last_update": "2024-04-20T14:14:28Z",
            "markets": [
              {
                "key": "h2h",
                "last_update": "2024-04-20T14:14:28Z",
                "outcomes": [
                  {
                    "name": "Delhi Capitals",
                    "price": 4.9
                  },
                  {
                    "name": "Sunrisers Hyderabad",
                    "price": 1.18
                  }
                ]
              }
            ]
          }
        ]
      }
    }
  },
  {
    "timestamp": "2024-04-20T14:25:00Z",
    "odds": {
      "timestamp": "2024-04-20T14:20:38Z",
      "previous_timestamp": "2024-04-20T14:15:39Z",
      "next_timestamp": "2024-04-20T14:25:38Z",
      "data": {
        "id": "a55f9238ff1d9711f6c35ab6d69cede0",
        "sport_key": "cricket_ipl",
        "sport_title": "IPL",
        "commence_time": "2024-04-20T14:00:00Z",
        "home_team": "Delhi Capitals",
        "away_team": "Sunrisers Hyderabad",
        "bookmakers": [
          {
            "key": "fanduel",
            "title": "FanDuel",
            "last_update": "2024-04-20T14:19:18Z",
            "markets": [
              {
                "key": "h2h",
                "last_update": "2024-04-20T14:19:18Z",
                "outcomes": [
                  {
                    "name": "Delhi Capitals",
                    "price": 6.5
                  },
                  {
                    "name": "Sunrisers Hyderabad",
                    "price": 1.11
                  }
                ]
              }
            ]
          }
        ]
      }
    }
  },
  {
    "timestamp": "2024-04-20T14:30:00Z",
    "odds": {
      "timestamp": "2024-04-20T14:25:38Z",
      "previous_timestamp": "2024-04-20T14:20:38Z",
      "next_timestamp": "2024-04-20T14:30:39Z",
      "data": {
        "id": "a55f9238ff1d9711f6c35ab6d69cede0",
        "sport_key": "cricket_ipl",
        "sport_title": "IPL",
        "commence_time": "2024-04-20T14:00:00Z",
        "home_team": "Delhi Capitals",
        "away_team": "Sunrisers Hyderabad",
        "bookmakers": [
          {
            "key": "fanduel",
            "title": "FanDuel",
            "last_update": "2024-04-20T14:20:46Z",
            "markets": [
              {
                "key": "h2h",
                "last_update": "2024-04-20T14:20:46Z",
                "outcomes": [
                  {
                    "name": "Delhi Capitals",
                    "price": 6.5
                  },
                  {
                    "name": "Sunrisers Hyderabad",
                    "price": 1.11
                  }
                ]
              }
            ]
          }
        ]
      }
    }
  },
  {
    "timestamp": "2024-04-20T14:35:00Z",
    "odds": {
      "timestamp": "2024-04-20T14:30:39Z",
      "previous_timestamp": "2024-04-20T14:25:38Z",
      "next_timestamp": "2024-04-20T14:35:39Z",
      "data": {
        "id": "a55f9238ff1d9711f6c35ab6d69cede0",
        "sport_key": "cricket_ipl",
        "sport_title": "IPL",
        "commence_time": "2024-04-20T14:00:00Z",
        "home_team": "Delhi Capitals",
        "away_team": "Sunrisers Hyderabad",
        "bookmakers": [
          {
            "key": "fanduel",
            "title": "FanDuel",
            "last_update": "2024-04-20T14:30:35Z",
            "markets": [
              {
                "key": "h2h",
                "last_update": "2024-04-20T14:30:35Z",
                "outcomes": [
                  {
                    "name": "Delhi Capitals",
                    "price": 11.0
                  },
                  {
                    "name": "Sunrisers Hyderabad",
                    "price": 1.04
                  }
                ]
              }
            ]
          }
        ]
      }
    }
  },
  {
    "timestamp": "2024-04-20T14:40:00Z",
    "odds": {
      "timestamp": "2024-04-20T14:35:39Z",
      "previous_timestamp": "2024-04-20T14:30:39Z",
      "next_timestamp": "2024-04-20T14:40:40Z",
      "data": {
        "id": "a55f9238ff1d9711f6c35ab6d69cede0",
        "sport_key": "cricket_ipl",
        "sport_title": "IPL",
        "commence_time": "2024-04-20T14:00:00Z",
        "home_team": "Delhi Capitals",
        "away_team": "Sunrisers Hyderabad",
        "bookmakers": [
          {
            "key": "fanduel",
            "title": "FanDuel",
            "last_update": "2024-04-20T14:30:35Z",
            "markets": [
              {
                "key": "h2h",
                "last_update": "2024-04-20T14:30:35Z",
                "outcomes": [
                  {
                    "name": "Delhi Capitals",
                    "price": 11.0
                  },
                  {
                    "name": "Sunrisers Hyderabad",
                    "price": 1.04
                  }
                ]
              }
            ]
          }
        ]
      }
    }
  },
  {
    "timestamp": "2024-04-20T14:45:00Z",
    "odds": {
      "timestamp": "2024-04-20T14:40:40Z",
      "previous_timestamp": "2024-04-20T14:35:39Z",
      "next_timestamp": "2024-04-20T14:45:38Z",
      "data": {
        "id": "a55f9238ff1d9711f6c35ab6d69cede0",
        "sport_key": "cricket_ipl",
        "sport_title": "IPL",
        "commence_time": "2024-04-20T14:00:00Z",
        "home_team": "Delhi Capitals",
        "away_team": "Sunrisers Hyderabad",
        "bookmakers": [
          {
            "key": "fanduel",
            "title": "FanDuel",
            "last_update": "2024-04-20T14:39:26Z",
            "markets": [
              {
                "key": "h2h",
                "last_update": "2024-04-20T14:39:26Z",
                "outcomes": [
                  {
                    "name": "Delhi Capitals",
                    "price": 7.5
                  },
                  {
                    "name": "Sunrisers Hyderabad",
                    "price": 1.08
                  }
                ]
              }
            ]
          }
        ]
      }
    }
  },
  {
    "timestamp": "2024-04-20T14:50:00Z",
    "odds": {
      "timestamp": "2024-04-20T14:45:38Z",
      "previous_timestamp": "2024-04-20T14:40:40Z",
      "next_timestamp": "2024-04-20T14:50:39Z",
      "data": {
        "id": "a55f9238ff1d9711f6c35ab6d69cede0",
        "sport_key": "cricket_ipl",
        "sport_title": "IPL",
        "commence_time": "2024-04-20T14:00:00Z",
        "home_team": "Delhi Capitals",
        "away_team": "Sunrisers Hyderabad",
        "bookmakers": [
          {
            "key": "fanduel",
            "title": "FanDuel",
            "last_update": "2024-04-20T14:45:33Z",
            "markets": [
              {
                "key": "h2h",
                "last_update": "2024-04-20T14:45:33Z",
                "outcomes": [
                  {
                    "name": "Delhi Capitals",
                    "price": 6.5
                  },
                  {
                    "name": "Sunrisers Hyderabad",
                    "price": 1.11
                  }
                ]
              }
            ]
          }
        ]
      }
    }
  },
  {
    "timestamp": "2024-04-20T14:55:00Z",
    "odds": {
      "timestamp": "2024-04-20T14:50:39Z",
      "previous_timestamp": "2024-04-20T14:45:38Z",
      "next_timestamp": "2024-04-20T14:55:38Z",
      "data": {
        "id": "a55f9238ff1d9711f6c35ab6d69cede0",
        "sport_key": "cricket_ipl",
        "sport_title": "IPL",
        "commence_time": "2024-04-20T14:00:00Z",
        "home_team": "Delhi Capitals",
        "away_team": "Sunrisers Hyderabad",
        "bookmakers": [
          {
            "key": "fanduel",
            "title": "FanDuel",
            "last_update": "2024-04-20T14:50:15Z",
            "markets": [
              {
                "key": "h2h",
                "last_update": "2024-04-20T14:50:15Z",
                "outcomes": [
                  {
                    "name": "Delhi Capitals",
                    "price": 4.3
                  },
                  {
                    "name": "Sunrisers Hyderabad",
                    "price": 1.22
                  }
                ]
              }
            ]
          }
        ]
      }
    }
  },
  {
    "timestamp": "2024-04-20T15:00:00Z",
    "odds": {
      "timestamp": "2024-04-20T14:55:38Z",
      "previous_timestamp": "2024-04-20T14:50:39Z",
      "next_timestamp": "2024-04-20T15:00:38Z",
      "data": {
        "id": "a55f9238ff1d9711f6c35ab6d69cede0",
        "sport_key": "cricket_ipl",
        "sport_title": "IPL",
        "commence_time": "2024-04-20T14:00:00Z",
        "home_team": "Delhi Capitals",
        "away_team": "Sunrisers Hyderabad",
        "bookmakers": [
          {
            "key": "fanduel",
            "title": "FanDuel",
            "last_update": "2024-04-20T14:54:45Z",
            "markets": [
              {
                "key": "h2h",
                "last_update": "2024-04-20T14:54:45Z",
                "outcomes": [
                  {
                    "name": "Delhi Capitals",
                    "price": 4.3
                  },
                  {
                    "name": "Sunrisers Hyderabad",
                    "price": 1.22
                  }
                ]
              }
            ]
          }
        ]
      }
    }
  },
  {
    "timestamp": "2024-04-20T15:05:00Z",
    "odds": {
      "timestamp": "2024-04-20T15:00:38Z",
      "previous_timestamp": "2024-04-20T14:55:38Z",
      "next_timestamp": "2024-04-20T15:05:39Z",
      "data": {
        "id": "a55f9238ff1d9711f6c35ab6d69cede0",
        "sport_key": "cricket_ipl",
        "sport_title": "IPL",
        "commence_time": "2024-04-20T14:00:00Z",
        "home_team": "Delhi Capitals",
        "away_team": "Sunrisers Hyderabad",
        "bookmakers": [
          {
            "key": "fanduel",
            "title": "FanDuel",
            "last_update": "2024-04-20T14:59:24Z",
            "markets": [
              {
                "key": "h2h",
                "last_update": "2024-04-20T14:59:24Z",
                "outcomes": [
                  {
                    "name": "Delhi Capitals",
                    "price": 5.5
                  },
                  {
                    "name": "Sunrisers Hyderabad",
                    "price": 1.15
                  }
                ]
              }
            ]
          }
        ]
      }
    }
  },
  {
    "timestamp": "2024-04-20T15:10:00Z",
    "odds": {
      "timestamp": "2024-04-20T15:05:39Z",
      "previous_timestamp": "2024-04-20T15:00:38Z",
      "next_timestamp": "2024-04-20T15:10:39Z",
      "data": {
        "id": "a55f9238ff1d9711f6c35ab6d69cede0",
        "sport_key": "cricket_ipl",
        "sport_title": "IPL",
        "commence_time": "2024-04-20T14:00:00Z",
        "home_team": "Delhi Capitals",
        "away_team": "Sunrisers Hyderabad",
        "bookmakers": [
          {
            "key": "fanduel",
            "title": "FanDuel",
            "last_update": "2024-04-20T15:05:35Z",
            "markets": [
              {
                "key": "h2h",
                "last_update": "2024-04-20T15:05:35Z",
                "outcomes": [
                  {
                    "name": "Delhi Capitals",
                    "price": 5.5
                  },
                  {
                    "name": "Sunrisers Hyderabad",
                    "price": 1.15
                  }
                ]
              }
            ]
          }
        ]
      }
    }
  },
  {
    "timestamp": "2024-04-20T15:15:00Z",
    "odds": {
      "timestamp": "2024-04-20T15:10:39Z",
      "previous_timestamp": "2024-04-20T15:05:39Z",
      "next_timestamp": "2024-04-20T15:15:39Z",
      "data": {
        "id": "a55f9238ff1d9711f6c35ab6d69cede0",
        "sport_key": "cricket_ipl",
        "sport_title": "IPL",
        "commence_time": "2024-04-20T14:00:00Z",
        "home_team": "Delhi Capitals",
        "away_team": "Sunrisers Hyderabad",
        "bookmakers": [
          {
            "key": "fanduel",
            "title": "FanDuel",
            "last_update": "2024-04-20T15:08:45Z",
            "markets": [
              {
                "key": "h2h",
                "last_update": "2024-04-20T15:08:45Z",
                "outcomes": [
                  {
                    "name": "Delhi Capitals",
                    "price": 6.0
                  },
                  {
                    "name": "Sunrisers Hyderabad",
                    "price": 1.13
                  }
                ]
              }
            ]
          }
        ]
      }
    }
  },
  {
    "timestamp": "2024-04-20T15:20:00Z",
    "odds": {
      "timestamp": "2024-04-20T15:15:39Z",
      "previous_timestamp": "2024-04-20T15:10:39Z",
      "next_timestamp": "2024-04-20T15:20:38Z",
      "data": {
        "id": "a55f9238ff1d9711f6c35ab6d69cede0",
        "sport_key": "cricket_ipl",
        "sport_title": "IPL",
        "commence_time": "2024-04-20T14:00:00Z",
        "home_team": "Delhi Capitals",
        "away_team": "Sunrisers Hyderabad",
        "bookmakers": [
          {
            "key": "fanduel",
            "title": "FanDuel",
            "last_update": "2024-04-20T15:15:00Z",
            "markets": [
              {
                "key": "h2h",
                "last_update": "2024-04-20T15:15:00Z",
                "outcomes": [
                  {
                    "name": "Delhi Capitals",
                    "price": 5.8
                  },
                  {
                    "name": "Sunrisers Hyderabad",
                    "price": 1.14
                  }
                ]
              }
            ]
          }
        ]
      }
    }
  },
  {
    "timestamp": "2024-04-20T15:25:00Z",
    "odds": {
      "timestamp": "2024-04-20T15:20:38Z",
      "previous_timestamp": "2024-04-20T15:15:39Z",
      "next_timestamp": "2024-04-20T15:25:39Z",
      "data": {
        "id": "a55f9238ff1d9711f6c35ab6d69cede0",
        "sport_key": "cricket_ipl",
        "sport_title": "IPL",
        "commence_time": "2024-04-20T14:00:00Z",
        "home_team": "Delhi Capitals",
        "away_team": "Sunrisers Hyderabad",
        "bookmakers": [
          {
            "key": "fanduel",
            "title": "FanDuel",
            "last_update": "2024-04-20T15:19:31Z",
            "markets": [
              {
                "key": "h2h",
                "last_update": "2024-04-20T15:19:31Z",
                "outcomes": [
                  {
                    "name": "Delhi Capitals",
                    "price": 6.0
                  },
                  {
                    "name": "Sunrisers Hyderabad",
                    "price": 1.12
                  }
                ]
              }
            ]
          }
        ]
      }
    }
  },
  {
    "timestamp": "2024-04-20T15:30:00Z",
    "odds": {
      "timestamp": "2024-04-20T15:25:39Z",
      "previous_timestamp": "2024-04-20T15:20:38Z",
      "next_timestamp": "2024-04-20T15:30:39Z",
      "data": {
        "id": "a55f9238ff1d9711f6c35ab6d69cede0",
        "sport_key": "cricket_ipl",
        "sport_title": "IPL",
        "commence_time": "2024-04-20T14:00:00Z",
        "home_team": "Delhi Capitals",
        "away_team": "Sunrisers Hyderabad",
        "bookmakers": [
          {
            "key": "fanduel",
            "title": "FanDuel",
            "last_update": "2024-04-20T15:24:06Z",
            "markets": [
              {
                "key": "h2h",
                "last_update": "2024-04-20T15:24:06Z",
                "outcomes": [
                  {
                    "name": "Delhi Capitals",
                    "price": 5.8
                  },
                  {
                    "name": "Sunrisers Hyderabad",
                    "price": 1.14
                  }
                ]
              }
            ]
          }
        ]
      }
    }
  },
  {
    "timestamp": "2024-04-20T15:35:00Z",
    "odds": {
      "timestamp": "2024-04-20T15:30:39Z",
      "previous_timestamp": "2024-04-20T15:25:39Z",
      "next_timestamp": "2024-04-20T15:35:39Z",
      "data": {
        "id": "a55f9238ff1d9711f6c35ab6d69cede0",
        "sport_key": "cricket_ipl",
        "sport_title": "IPL",
        "commence_time": "2024-04-20T14:00:00Z",
        "home_team": "Delhi Capitals",
        "away_team": "Sunrisers Hyderabad",
        "bookmakers": [
          {
            "key": "fanduel",
            "title": "FanDuel",
            "last_update": "2024-04-20T15:30:16Z",
            "markets": [
              {
                "key": "h2h",
                "last_update": "2024-04-20T15:30:16Z",
                "outcomes": [
                  {
                    "name": "Delhi Capitals",
                    "price": 6.0
                  },
                  {
                    "name": "Sunrisers Hyderabad",
                    "price": 1.12
                  }
                ]
              }
            ]
          }
        ]
      }
    }
  },
  {
    "timestamp": "2024-04-20T15:40:00Z",
    "odds": {
      "timestamp": "2024-04-20T15:35:39Z",
      "previous_timestamp": "2024-04-20T15:30:39Z",
      "next_timestamp": "2024-04-20T15:40:38Z",
      "data": {
        "id": "a55f9238ff1d9711f6c35ab6d69cede0",
        "sport_key": "cricket_ipl",
        "sport_title": "IPL",
        "commence_time": "2024-04-20T14:00:00Z",
        "home_team": "Delhi Capitals",
        "away_team": "Sunrisers Hyderabad",
        "bookmakers": [
          {
            "key": "fanduel",
            "title": "FanDuel",
            "last_update": "2024-04-20T15:34:54Z",
            "markets": [
              {
                "key": "h2h",
                "last_update": "2024-04-20T15:34:54Z",
                "outcomes": [
                  {
                    "name": "Delhi Capitals",
                    "price": 5.6
                  },
                  {
                    "name": "Sunrisers Hyderabad",
                    "price": 1.14
                  }
                ]
              }
            ]
          }
        ]
      }
    }
  },
  {
    "timestamp": "2024-04-20T15:45:00Z",
    "odds": {
      "timestamp": "2024-04-20T15:40:38Z",
      "previous_timestamp": "2024-04-20T15:35:39Z",
      "next_timestamp": "2024-04-20T15:45:39Z",
      "data": {
        "id": "a55f9238ff1d9711f6c35ab6d69cede0",
        "sport_key": "cricket_ipl",
        "sport_title": "IPL",
        "commence_time": "2024-04-20T14:00:00Z",
        "home_team": "Delhi Capitals",
        "away_team": "Sunrisers Hyderabad",
        "bookmakers": [
          {
            "key": "fanduel",
            "title": "FanDuel",
            "last_update": "2024-04-20T15:39:44Z",
            "markets": [
              {
                "key": "h2h",
                "last_update": "2024-04-20T15:39:44Z",
                "outcomes": [
                  {
                    "name": "Delhi Capitals",
                    "price": 6.5
                  },
                  {
                    "name": "Sunrisers Hyderabad",
                    "price": 1.11
                  }
                ]
              }
            ]
          }
        ]
      }
    }
  },
  {
    "timestamp": "2024-04-20T15:50:00Z",
    "odds": {
      "timestamp": "2024-04-20T15:45:39Z",
      "previous_timestamp": "2024-04-20T15:40:38Z",
      "next_timestamp": "2024-04-20T15:50:38Z",
      "data": {
        "id": "a55f9238ff1d9711f6c35ab6d69cede0",
        "sport_key": "cricket_ipl",
        "sport_title": "IPL",
        "commence_time": "2024-04-20T14:00:00Z",
        "home_team": "Delhi Capitals",
        "away_team": "Sunrisers Hyderabad",
        "bookmakers": [
          {
            "key": "fanduel",
            "title": "FanDuel",
            "last_update": "2024-04-20T15:44:19Z",
            "markets": [
              {
                "key": "h2h",
                "last_update": "2024-04-20T15:44:19Z",
                "outcomes": [
                  {
                    "name": "Delhi Capitals",
                    "price": 6.0
                  },
                  {
                    "name": "Sunrisers Hyderabad",
                    "price": 1.12
                  }
                ]
              }
            ]
          }
        ]
      }
    }
  },
  {
    "timestamp": "2024-04-20T15:55:00Z",
    "odds": {
      "timestamp": "2024-04-20T15:50:38Z",
      "previous_timestamp": "2024-04-20T15:45:39Z",
      "next_timestamp": "2024-04-20T15:55:39Z",
      "data": {
        "id": "a55f9238ff1d9711f6c35ab6d69cede0",
        "sport_key": "cricket_ipl",
        "sport_title": "IPL",
        "commence_time": "2024-04-20T14:00:00Z",
        "home_team": "Delhi Capitals",
        "away_team": "Sunrisers Hyderabad",
        "bookmakers": [
          {
            "key": "fanduel",
            "title": "FanDuel",
            "last_update": "2024-04-20T15:50:29Z",
            "markets": [
              {
                "key": "h2h",
                "last_update": "2024-04-20T15:50:29Z",
                "outcomes": [
                  {
                    "name": "Delhi Capitals",
                    "price": 7.5
                  },
                  {
                    "name": "Sunrisers Hyderabad",
                    "price": 1.09
                  }
                ]
              }
            ]
          }
        ]
      }
    }
  },
  {
    "timestamp": "2024-04-20T16:00:00Z",
    "odds": {
      "timestamp": "2024-04-20T15:55:39Z",
      "previous_timestamp": "2024-04-20T15:50:38Z",
      "next_timestamp": "2024-04-20T16:00:38Z",
      "data": {
        "id": "a55f9238ff1d9711f6c35ab6d69cede0",
        "sport_key": "cricket_ipl",
        "sport_title": "IPL",
        "commence_time": "2024-04-20T14:00:00Z",
        "home_team": "Delhi Capitals",
        "away_team": "Sunrisers Hyderabad",
        "bookmakers": [
          {
            "key": "fanduel",
            "title": "FanDuel",
            "last_update": "2024-04-20T15:55:15Z",
            "markets": [
              {
                "key": "h2h",
                "last_update": "2024-04-20T15:55:15Z",
                "outcomes": [
                  {
                    "name": "Delhi Capitals",
                    "price": 6.5
                  },
                  {
                    "name": "Sunrisers Hyderabad",
                    "price": 1.11
                  }
                ]
              }
            ]
          }
        ]
      }
    }
  },
  {
    "timestamp": "2024-04-20T16:05:00Z",
    "odds": {
      "timestamp": "2024-04-20T16:00:38Z",
      "previous_timestamp": "2024-04-20T15:55:39Z",
      "next_timestamp": "2024-04-20T16:05:38Z",
      "data": {
        "id": "a55f9238ff1d9711f6c35ab6d69cede0",
        "sport_key": "cricket_ipl",
        "sport_title": "IPL",
        "commence_time": "2024-04-20T14:00:00Z",
        "home_team": "Delhi Capitals",
        "away_team": "Sunrisers Hyderabad",
        "bookmakers": [
          {
            "key": "fanduel",
            "title": "FanDuel",
            "last_update": "2024-04-20T15:58:27Z",
            "markets": [
              {
                "key": "h2h",
                "last_update": "2024-04-20T15:58:27Z",
                "outcomes": [
                  {
                    "name": "Delhi Capitals",
                    "price": 6.5
                  },
                  {
                    "name": "Sunrisers Hyderabad",
                    "price": 1.11
                  }
                ]
              }
            ]
          }
        ]
      }
    }
  },
  {
    "timestamp": "2024-04-20T16:10:00Z",
    "odds": {
      "timestamp": "2024-04-20T16:05:38Z",
      "previous_timestamp": "2024-04-20T16:00:38Z",
      "next_timestamp": "2024-04-20T16:10:39Z",
      "data": {
        "id": "a55f9238ff1d9711f6c35ab6d69cede0",
        "sport_key": "cricket_ipl",
        "sport_title": "IPL",
        "commence_time": "2024-04-20T14:00:00Z",
        "home_team": "Delhi Capitals",
        "away_team": "Sunrisers Hyderabad",
        "bookmakers": [
          {
            "key": "fanduel",
            "title": "FanDuel",
            "last_update": "2024-04-20T16:04:35Z",
            "markets": [
              {
                "key": "h2h",
                "last_update": "2024-04-20T16:04:35Z",
                "outcomes": [
                  {
                    "name": "Delhi Capitals",
                    "price": 6.0
                  },
                  {
                    "name": "Sunrisers Hyderabad",
                    "price": 1.12
                  }
                ]
              }
            ]
          }
        ]
      }
    }
  },
  {
    "timestamp": "2024-04-20T16:15:00Z",
    "odds": {
      "timestamp": "2024-04-20T16:10:39Z",
      "previous_timestamp": "2024-04-20T16:05:38Z",
      "next_timestamp": "2024-04-20T16:15:39Z",
      "data": {
        "id": "a55f9238ff1d9711f6c35ab6d69cede0",
        "sport_key": "cricket_ipl",
        "sport_title": "IPL",
        "commence_time": "2024-04-20T14:00:00Z",
        "home_team": "Delhi Capitals",
        "away_team": "Sunrisers Hyderabad",
        "bookmakers": [
          {
            "key": "fanduel",
            "title": "FanDuel",
            "last_update": "2024-04-20T16:09:04Z",
            "markets": [
              {
                "key": "h2h",
                "last_update": "2024-04-20T16:09:04Z",
                "outcomes": [
                  {
                    "name": "Delhi Capitals",
                    "price": 5.7
                  },
                  {
                    "name": "Sunrisers Hyderabad",
                    "price": 1.14
                  }
                ]
              }
            ]
          }
        ]
      }
    }
  },
  {
    "timestamp": "2024-04-20T16:20:00Z",
    "odds": {
      "timestamp": "2024-04-20T16:15:39Z",
      "previous_timestamp": "2024-04-20T16:10:39Z",
      "next_timestamp": "2024-04-20T16:20:38Z",
      "data": {
        "id": "a55f9238ff1d9711f6c35ab6d69cede0",
        "sport_key": "cricket_ipl",
        "sport_title": "IPL",
        "commence_time": "2024-04-20T14:00:00Z",
        "home_team": "Delhi Capitals",
        "away_team": "Sunrisers Hyderabad",
        "bookmakers": [
          {
            "key": "fanduel",
            "title": "FanDuel",
            "last_update": "2024-04-20T16:13:50Z",
            "markets": [
              {
                "key": "h2h",
                "last_update": "2024-04-20T16:13:50Z",
                "outcomes": [
                  {
                    "name": "Delhi Capitals",
                    "price": 6.0
                  },
                  {
                    "name": "Sunrisers Hyderabad",
                    "price": 1.12
                  }
                ]
              }
            ]
          }
        ]
      }
    }
  },
  {
    "timestamp": "2024-04-20T16:25:00Z",
    "odds": {
      "timestamp": "2024-04-20T16:20:38Z",
      "previous_timestamp": "2024-04-20T16:15:39Z",
      "next_timestamp": "2024-04-20T16:25:38Z",
      "data": {
        "id": "a55f9238ff1d9711f6c35ab6d69cede0",
        "sport_key": "cricket_ipl",
        "sport_title": "IPL",
        "commence_time": "2024-04-20T14:00:00Z",
        "home_team": "Delhi Capitals",
        "away_team": "Sunrisers Hyderabad",
        "bookmakers": [
          {
            "key": "fanduel",
            "title": "FanDuel",
            "last_update": "2024-04-20T16:18:28Z",
            "markets": [
              {
                "key": "h2h",
                "last_update": "2024-04-20T16:18:28Z",
                "outcomes": [
                  {
                    "name": "Delhi Capitals",
                    "price": 5.6
                  },
                  {
                    "name": "Sunrisers Hyderabad",
                    "price": 1.15
                  }
                ]
              }
            ]
          }
        ]
      }
    }
  },
  {
    "timestamp": "2024-04-20T16:30:00Z",
    "odds": {
      "timestamp": "2024-04-20T16:25:38Z",
      "previous_timestamp": "2024-04-20T16:20:38Z",
      "next_timestamp": "2024-04-20T16:30:39Z",
      "data": {
        "id": "a55f9238ff1d9711f6c35ab6d69cede0",
        "sport_key": "cricket_ipl",
        "sport_title": "IPL",
        "commence_time": "2024-04-20T14:00:00Z",
        "home_team": "Delhi Capitals",
        "away_team": "Sunrisers Hyderabad",
        "bookmakers": [
          {
            "key": "fanduel",
            "title": "FanDuel",
            "last_update": "2024-04-20T16:23:29Z",
            "markets": [
              {
                "key": "h2h",
                "last_update": "2024-04-20T16:23:29Z",
                "outcomes": [
                  {
                    "name": "Delhi Capitals",
                    "price": 4.1
                  },
                  {
                    "name": "Sunrisers Hyderabad",
                    "price": 1.24
                  }
                ]
              }
            ]
          }
        ]
      }
    }
  },
  {
    "timestamp": "2024-04-20T16:35:00Z",
    "odds": {
      "timestamp": "2024-04-20T16:30:39Z",
      "previous_timestamp": "2024-04-20T16:25:38Z",
      "next_timestamp": "2024-04-20T16:35:38Z",
      "data": {
        "id": "a55f9238ff1d9711f6c35ab6d69cede0",
        "sport_key": "cricket_ipl",
        "sport_title": "IPL",
        "commence_time": "2024-04-20T14:00:00Z",
        "home_team": "Delhi Capitals",
        "away_team": "Sunrisers Hyderabad",
        "bookmakers": [
          {
            "key": "fanduel",
            "title": "FanDuel",
            "last_update": "2024-04-20T16:29:36Z",
            "markets": [
              {
                "key": "h2h",
                "last_update": "2024-04-20T16:29:36Z",
                "outcomes": [
                  {
                    "name": "Delhi Capitals",
                    "price": 5.5
                  },
                  {
                    "name": "Sunrisers Hyderabad",
                    "price": 1.15
                  }
                ]
              }
            ]
          }
        ]
      }
    }
  },
  {
    "timestamp": "2024-04-20T16:40:00Z",
    "odds": {
      "timestamp": "2024-04-20T16:35:38Z",
      "previous_timestamp": "2024-04-20T16:30:39Z",
      "next_timestamp": "2024-04-20T16:40:39Z",
      "data": {
        "id": "a55f9238ff1d9711f6c35ab6d69cede0",
        "sport_key": "cricket_ipl",
        "sport_title": "IPL",
        "commence_time": "2024-04-20T14:00:00Z",
        "home_team": "Delhi Capitals",
        "away_team": "Sunrisers Hyderabad",
        "bookmakers": [
          {
            "key": "fanduel",
            "title": "FanDuel",
            "last_update": "2024-04-20T16:34:16Z",
            "markets": [
              {
                "key": "h2h",
                "last_update": "2024-04-20T16:34:16Z",
                "outcomes": [
                  {
                    "name": "Delhi Capitals",
                    "price": 3.2
                  },
                  {
                    "name": "Sunrisers Hyderabad",
                    "price": 1.36
                  }
                ]
              }
            ]
          }
        ]
      }
    }
  },
  {
    "timestamp": "2024-04-20T16:45:00Z",
    "odds": {
      "timestamp": "2024-04-20T16:40:39Z",
      "previous_timestamp": "2024-04-20T16:35:38Z",
      "next_timestamp": "2024-04-20T16:45:38Z",
      "data": {
        "id": "a55f9238ff1d9711f6c35ab6d69cede0",
        "sport_key": "cricket_ipl",
        "sport_title": "IPL",
        "commence_time": "2024-04-20T14:00:00Z",
        "home_team": "Delhi Capitals",
        "away_team": "Sunrisers Hyderabad",
        "bookmakers": [
          {
            "key": "fanduel",
            "title": "FanDuel",
            "last_update": "2024-04-20T16:40:32Z",
            "markets": [
              {
                "key": "h2h",
                "last_update": "2024-04-20T16:40:32Z",
                "outcomes": [
                  {
                    "name": "Delhi Capitals",
                    "price": 3.0
                  },
                  {
                    "name": "Sunrisers Hyderabad",
                    "price": 1.38
                  }
                ]
              }
            ]
          }
        ]
      }
    }
  },
  {
    "timestamp": "2024-04-20T16:50:00Z",
    "odds": {
      "timestamp": "2024-04-20T16:45:38Z",
      "previous_timestamp": "2024-04-20T16:40:39Z",
      "next_timestamp": "2024-04-20T16:50:38Z",
      "data": {
        "id": "a55f9238ff1d9711f6c35ab6d69cede0",
        "sport_key": "cricket_ipl",
        "sport_title": "IPL",
        "commence_time": "2024-04-20T14:00:00Z",
        "home_team": "Delhi Capitals",
        "away_team": "Sunrisers Hyderabad",
        "bookmakers": [
          {
            "key": "fanduel",
            "title": "FanDuel",
            "last_update": "2024-04-20T16:45:08Z",
            "markets": [
              {
                "key": "h2h",
                "last_update": "2024-04-20T16:45:08Z",
                "outcomes": [
                  {
                    "name": "Delhi Capitals",
                    "price": 4.0
                  },
                  {
                    "name": "Sunrisers Hyderabad",
                    "price": 1.24
                  }
                ]
              }
            ]
          }
        ]
      }
    }
  },
  {
    "timestamp": "2024-04-20T16:55:00Z",
    "odds": {
      "timestamp": "2024-04-20T16:50:38Z",
      "previous_timestamp": "2024-04-20T16:45:38Z",
      "next_timestamp": "2024-04-20T16:55:39Z",
      "data": {
        "id": "a55f9238ff1d9711f6c35ab6d69cede0",
        "sport_key": "cricket_ipl",
        "sport_title": "IPL",
        "commence_time": "2024-04-20T14:00:00Z",
        "home_team": "Delhi Capitals",
        "away_team": "Sunrisers Hyderabad",
        "bookmakers": [
          {
            "key": "fanduel",
            "title": "FanDuel",
            "last_update": "2024-04-20T16:49:43Z",
            "markets": [
              {
                "key": "h2h",
                "last_update": "2024-04-20T16:49:43Z",
                "outcomes": [
                  {
                    "name": "Delhi Capitals",
                    "price": 5.2
                  },
                  {
                    "name": "Sunrisers Hyderabad",
                    "price": 1.17
                  }
                ]
              }
            ]
          }
        ]
      }
    }
  },
  {
    "timestamp": "2024-04-20T17:00:00Z",
    "odds": {
      "timestamp": "2024-04-20T16:55:39Z",
      "previous_timestamp": "2024-04-20T16:50:38Z",
      "next_timestamp": "2024-04-20T17:00:39Z",
      "data": {
        "id": "a55f9238ff1d9711f6c35ab6d69cede0",
        "sport_key": "cricket_ipl",
        "sport_title": "IPL",
        "commence_time": "2024-04-20T14:00:00Z",
        "home_team": "Delhi Capitals",
        "away_team": "Sunrisers Hyderabad",
        "bookmakers": [
          {
            "key": "fanduel",
            "title": "FanDuel",
            "last_update": "2024-04-20T16:54:29Z",
            "markets": [
              {
                "key": "h2h",
                "last_update": "2024-04-20T16:54:29Z",
                "outcomes": [
                  {
                    "name": "Delhi Capitals",
                    "price": 5.8
                  },
                  {
                    "name": "Sunrisers Hyderabad",
                    "price": 1.14
                  }
                ]
              }
            ]
          }
        ]
      }
    }
  },
  {
    "timestamp": "2024-04-20T17:05:00Z",
    "odds": {
      "timestamp": "2024-04-20T17:00:39Z",
      "previous_timestamp": "2024-04-20T16:55:39Z",
      "next_timestamp": "2024-04-20T17:05:38Z",
      "data": {
        "id": "a55f9238ff1d9711f6c35ab6d69cede0",
        "sport_key": "cricket_ipl",
        "sport_title": "IPL",
        "commence_time": "2024-04-20T14:00:00Z",
        "home_team": "Delhi Capitals",
        "away_team": "Sunrisers Hyderabad",
        "bookmakers": [
          {
            "key": "fanduel",
            "title": "FanDuel",
            "last_update": "2024-04-20T16:57:28Z",
            "markets": [
              {
                "key": "h2h",
                "last_update": "2024-04-20T16:57:28Z",
                "outcomes": [
                  {
                    "name": "Delhi Capitals",
                    "price": 5.1
                  },
                  {
                    "name": "Sunrisers Hyderabad",
                    "price": 1.18
                  }
                ]
              }
            ]
          }
        ]
      }
    }
  },
  {
    "timestamp": "2024-04-20T17:10:00Z",
    "odds": {
      "timestamp": "2024-04-20T17:05:38Z",
      "previous_timestamp": "2024-04-20T17:00:39Z",
      "next_timestamp": "2024-04-20T17:10:38Z",
      "data": {
        "id": "a55f9238ff1d9711f6c35ab6d69cede0",
        "sport_key": "cricket_ipl",
        "sport_title": "IPL",
        "commence_time": "2024-04-20T14:00:00Z",
        "home_team": "Delhi Capitals",
        "away_team": "Sunrisers Hyderabad",
        "bookmakers": [
          {
            "key": "fanduel",
            "title": "FanDuel",
            "last_update": "2024-04-20T17:04:56Z",
            "markets": [
              {
                "key": "h2h",
                "last_update": "2024-04-20T17:04:56Z",
                "outcomes": [
                  {
                    "name": "Delhi Capitals",
                    "price": 13.0
                  },
                  {
                    "name": "Sunrisers Hyderabad",
                    "price": 1.03
                  }
                ]
              }
            ]
          }
        ]
      }
    }
  },
  {
    "timestamp": "2024-04-20T17:15:00Z",
    "odds": {
      "timestamp": "2024-04-20T17:10:38Z",
      "previous_timestamp": "2024-04-20T17:05:38Z",
      "next_timestamp": "2024-04-20T17:15:39Z",
      "data": {
        "id": "a55f9238ff1d9711f6c35ab6d69cede0",
        "sport_key": "cricket_ipl",
        "sport_title": "IPL",
        "commence_time": "2024-04-20T14:00:00Z",
        "home_team": "Delhi Capitals",
        "away_team": "Sunrisers Hyderabad",
        "bookmakers": [
          {
            "key": "fanduel",
            "title": "FanDuel",
            "last_update": "2024-04-20T17:09:29Z",
            "markets": [
              {
                "key": "h2h",
                "last_update": "2024-04-20T17:09:29Z",
                "outcomes": [
                  {
                    "name": "Delhi Capitals",
                    "price": 31.0
                  },
                  {
                    "name": "Sunrisers Hyderabad",
                    "price": 1.01
                  }
                ]
              }
            ]
          }
        ]
      }
    }
  },
  {
    "timestamp": "2024-04-20T17:20:00Z",
    "odds": {
      "timestamp": "2024-04-20T17:15:39Z",
      "previous_timestamp": "2024-04-20T17:10:38Z",
      "next_timestamp": "2024-04-20T17:20:38Z",
      "data": {
        "id": "a55f9238ff1d9711f6c35ab6d69cede0",
        "sport_key": "cricket_ipl",
        "sport_title": "IPL",
        "commence_time": "2024-04-20T14:00:00Z",
        "home_team": "Delhi Capitals",
        "away_team": "Sunrisers Hyderabad",
        "bookmakers": [
          {
            "key": "fanduel",
            "title": "FanDuel",
            "last_update": "2024-04-20T17:14:04Z",
            "markets": [
              {
                "key": "h2h",
                "last_update": "2024-04-20T17:14:04Z",
                "outcomes": [
                  {
                    "name": "Delhi Capitals",
                    "price": 31.0
                  },
                  {
                    "name": "Sunrisers Hyderabad",
                    "price": 1.01
                  }
                ]
              }
            ]
          }
        ]
      }
    }
  },
  {
    "timestamp": "2024-04-20T17:25:00Z",
    "odds": {
      "timestamp": "2024-04-20T17:20:38Z",
      "previous_timestamp": "2024-04-20T17:15:39Z",
      "next_timestamp": "2024-04-20T17:25:39Z",
      "data": {
        "id": "a55f9238ff1d9711f6c35ab6d69cede0",
        "sport_key": "cricket_ipl",
        "sport_title": "IPL",
        "commence_time": "2024-04-20T14:00:00Z",
        "home_team": "Delhi Capitals",
        "away_team": "Sunrisers Hyderabad",
        "bookmakers": [
          {
            "key": "fanduel",
            "title": "FanDuel",
            "last_update": "2024-04-20T17:14:04Z",
            "markets": [
              {
                "key": "h2h",
                "last_update": "2024-04-20T17:14:04Z",
                "outcomes": [
                  {
                    "name": "Delhi Capitals",
                    "price": 31.0
                  },
                  {
                    "name": "Sunrisers Hyderabad",
                    "price": 1.01
                  }
                ]
              }
            ]
          }
        ]
      }
    }
  }
]