[
  {
    "timestamp": "2024-04-21T10:00:00Z",
    "odds": {
      "timestamp": "2024-04-21T09:55:38Z",
      "previous_timestamp": "2024-04-21T09:50:38Z",
      "next_timestamp": "2024-04-21T10:00:38Z",
      "data": {
        "id": "41a7ce09d7c82193024084293f2a8f9e",
        "sport_key": "cricket_ipl",
        "sport_title": "IPL",
        "commence_time": "2024-04-21T10:00:00Z",
        "home_team": "Kolkata Knight Riders",
        "away_team": "Royal Challengers Bangalore",
        "bookmakers": [
          {
            "key": "draftkings",
            "title": "DraftKings",
            "last_update": "2024-04-21T09:55:07Z",
            "markets": [
              {
                "key": "h2h",
                "last_update": "2024-04-21T09:55:07Z",
                "outcomes": [
                  {
                    "name": "Kolkata Knight Riders",
                    "price": 1.69
                  },
                  {
                    "name": "Royal Challengers Bangalore",
                    "price": 2.15
                  }
                ]
              }
            ]
          }
        ]
      }
    }
  },
  {
    "timestamp": "2024-04-21T10:05:00Z",
    "odds": {
      "timestamp": "2024-04-21T10:00:38Z",
      "previous_timestamp": "2024-04-21T09:55:38Z",
      "next_timestamp": "2024-04-21T10:05:38Z",
      "data": {
        "id": "41a7ce09d7c82193024084293f2a8f9e",
        "sport_key": "cricket_ipl",
        "sport_title": "IPL",
        "commence_time": "2024-04-21T10:00:00Z",
        "home_team": "Kolkata Knight Riders",
        "away_team": "Royal Challengers Bangalore",
        "bookmakers": [
          {
            "key": "draftkings",
            "title": "DraftKings",
            "last_update": "2024-04-21T09:59:44Z",
            "markets": [
              {
                "key": "h2h",
                "last_update": "2024-04-21T09:59:44Z",
                "outcomes": [
                  {
                    "name": "Kolkata Knight Riders",
                    "price": 1.67
                  },
                  {
                    "name": "Royal Challengers Bangalore",
                    "price": 2.2
                  }
                ]
              }
            ]
          }
        ]
      }
    }
  },
  {
    "timestamp": "2024-04-21T10:10:00Z",
    "odds": {
      "timestamp": "2024-04-21T10:05:38Z",
      "previous_timestamp": "2024-04-21T10:00:38Z",
      "next_timestamp": "2024-04-21T10:10:38Z",
      "data": {
        "id": "41a7ce09d7c82193024084293f2a8f9e",
        "sport_key": "cricket_ipl",
        "sport_title": "IPL",
        "commence_time": "2024-04-21T10:00:00Z",
        "home_team": "Kolkata Knight Riders",
        "away_team": "Royal Challengers Bangalore",
        "bookmakers": [
          {
            "key": "draftkings",
            "title": "DraftKings",
            "last_update": "2024-04-21T10:04:45Z",
            "markets": [
              {
                "key": "h2h",
                "last_update": "2024-04-21T10:04:45Z",
                "outcomes": [
                  {
                    "name": "Kolkata Knight Riders",
                    "price": 1.53
                  },
                  {
                    "name": "Royal Challengers Bangalore",
                    "price": 2.5
                  }
                ]
              }
            ]
          }
        ]
      }
    }
  },
  {
    "timestamp": "2024-04-21T10:15:00Z",
    "odds": {
      "timestamp": "2024-04-21T10:10:38Z",
      "previous_timestamp": "2024-04-21T10:05:38Z",
      "next_timestamp": "2024-04-21T10:15:38Z",
      "data": {
        "id": "41a7ce09d7c82193024084293f2a8f9e",
        "sport_key": "cricket_ipl",
        "sport_title": "IPL",
        "commence_time": "2024-04-21T10:00:00Z",
        "home_team": "Kolkata Knight Riders",
        "away_team": "Royal Challengers Bangalore",
        "bookmakers": [
          {
            "key": "draftkings",
            "title": "DraftKings",
            "last_update": "2024-04-21T10:10:34Z",
            "markets": [
              {
                "key": "h2h",
                "last_update": "2024-04-21T10:10:34Z",
                "outcomes": [
                  {
                    "name": "Kolkata Knight Riders",
                    "price": 1.62
                  },
                  {
                    "name": "Royal Challengers Bangalore",
                    "price": 2.3
                  }
                ]
              }
            ]
          }
        ]
      }
    }
  },
  {
    "timestamp": "2024-04-21T10:20:00Z",
    "odds": {
      "timestamp": "2024-04-21T10:15:38Z",
      "previous_timestamp": "2024-04-21T10:10:38Z",
      "next_timestamp": "2024-04-21T10:20:38Z",
      "data": {
        "id": "41a7ce09d7c82193024084293f2a8f9e",
        "sport_key": "cricket_ipl",
        "sport_title": "IPL",
        "commence_time": "2024-04-21T10:00:00Z",
        "home_team": "Kolkata Knight Riders",
        "away_team": "Royal Challengers Bangalore",
        "bookmakers": [
          {
            "key": "draftkings",
            "title": "DraftKings",
            "last_update": "2024-04-21T10:14:38Z",
            "markets": [
              {
                "key": "h2h",
                "last_update": "2024-04-21T10:14:38Z",
                "outcomes": [
                  {
                    "name": "Kolkata Knight Riders",
                    "price": 1.56
                  },
                  {
                    "name": "Royal Challengers Bangalore",
                    "price": 2.45
                  }
                ]
              }
            ]
          }
        ]
      }
    }
  },
  {
    "timestamp": "2024-04-21T10:25:00Z",
    "odds": {
      "timestamp": "2024-04-21T10:20:38Z",
      "previous_timestamp": "2024-04-21T10:15:38Z",
      "next_timestamp": "2024-04-21T10:25:38Z",
      "data": {
        "id": "41a7ce09d7c82193024084293f2a8f9e",
        "sport_key": "cricket_ipl",
        "sport_title": "IPL",
        "commence_time": "2024-04-21T10:00:00Z",
        "home_team": "Kolkata Knight Riders",
        "away_team": "Royal Challengers Bangalore",
        "bookmakers": [
          {
            "key": "draftkings",
            "title": "DraftKings",
            "last_update": "2024-04-21T10:18:59Z",
            "markets": [
              {
                "key": "h2h",
                "last_update": "2024-04-21T10:18:59Z",
                "outcomes": [
                  {
                    "name": "Kolkata Knight Riders",
                    "price": 1.61
                  },
                  {
                    "name": "Royal Challengers Bangalore",
                    "price": 2.35
                  }
                ]
              }
            ]
          }
        ]
      }
    }
  },
  {
    "timestamp": "2024-04-21T10:30:00Z",
    "odds": {
      "timestamp": "2024-04-21T10:25:38Z",
      "previous_timestamp": "2024-04-21T10:20:38Z",
      "next_timestamp": "2024-04-21T10:30:38Z",
      "data": {
        "id": "41a7ce09d7c82193024084293f2a8f9e",
        "sport_key": "cricket_ipl",
        "sport_title": "IPL",
        "commence_time": "2024-04-21T10:00:00Z",
        "home_team": "Kolkata Knight Riders",
        "away_team": "Royal Challengers Bangalore",
        "bookmakers": [
          {
            "key": "draftkings",
            "title": "DraftKings",
            "last_update": "2024-04-21T10:24:14Z",
            "markets": [
              {
                "key": "h2h",
                "last_update": "2024-04-21T10:24:14Z",
                "outcomes": [
                  {
                    "name": "Kolkata Knight Riders",
                    "price": 1.34
                  },
                  {
                    "name": "Royal Challengers Bangalore",
                    "price": 3.25
                  }
                ]
              }
            ]
          }
        ]
      }
    }
  },
  {
    "timestamp": "2024-04-21T10:35:00Z",
    "odds": {
      "timestamp": "2024-04-21T10:30:38Z",
      "previous_timestamp": "2024-04-21T10:25:38Z",
      "next_timestamp": "2024-04-21T10:35:38Z",
      "data": {
        "id": "41a7ce09d7c82193024084293f2a8f9e",
        "sport_key": "cricket_ipl",
        "sport_title": "IPL",
        "commence_time": "2024-04-21T10:00:00Z",
        "home_team": "Kolkata Knight Riders",
        "away_team": "Royal Challengers Bangalore",
        "bookmakers": [
          {
            "key": "draftkings",
            "title": "DraftKings",
            "last_update": "2024-04-21T10:28:50Z",
            "markets": [
              {
                "key": "h2h",
                "last_update": "2024-04-21T10:28:50Z",
                "outcomes": [
                  {
                    "name": "Kolkata Knight Riders",
                    "price": 1.43
                  },
                  {
                    "name": "Royal Challengers Bangalore",
                    "price": 2.8
                  }
                ]
              }
            ]
          }
        ]
      }
    }
  },
  {
    "timestamp": "2024-04-21T10:40:00Z",
    "odds": {
      "timestamp": "2024-04-21T10:35:38Z",
      "previous_timestamp": "2024-04-21T10:30:38Z",
      "next_timestamp": "2024-04-21T10:40:38Z",
      "data": {
        "id": "41a7ce09d7c82193024084293f2a8f9e",
        "sport_key": "cricket_ipl",
        "sport_title": "IPL",
        "commence_time": "2024-04-21T10:00:00Z",
        "home_team": "Kolkata Knight Riders",
        "away_team": "Royal Challengers Bangalore",
        "bookmakers": [
          {
            "key": "draftkings",
            "title": "DraftKings",
            "last_update": "2024-04-21T10:35:30Z",
            "markets": [
              {
                "key": "h2h",
                "last_update": "2024-04-21T10:35:30Z",
                "outcomes": [
                  {
                    "name": "Kolkata Knight Riders",
                    "price": 1.41
                  },
                  {
                    "name": "Royal Challengers Bangalore",
                    "price": 3.0
                  }
                ]
              }
            ]
          }
        ]
      }
    }
  },
  {
    "timestamp": "2024-04-21T10:45:00Z",
    "odds": {
      "timestamp": "2024-04-21T10:40:38Z",
      "previous_timestamp": "2024-04-21T10:35:38Z",
      "next_timestamp": "2024-04-21T10:45:38Z",
      "data": {
        "id": "41a7ce09d7c82193024084293f2a8f9e",
        "sport_key": "cricket_ipl",
        "sport_title": "IPL",
        "commence_time": "2024-04-21T10:00:00Z",
        "home_team": "Kolkata Knight Riders",
        "away_team": "Royal Challengers Bangalore",
        "bookmakers": [
          {
            "key": "draftkings",
            "title": "DraftKings",
            "last_update": "2024-04-21T10:39:16Z",
            "markets": [
              {
                "key": "h2h",
                "last_update": "2024-04-21T10:39:16Z",
                "outcomes": [
                  {
                    "name": "Kolkata Knight Riders",
                    "price": 1.57
                  },
                  {
                    "name": "Royal Challengers Bangalore",
                    "price": 2.4
                  }
                ]
              }
            ]
          }
        ]
      }
    }
  },
  {
    "timestamp": "2024-04-21T10:50:00Z",
    "odds": {
      "timestamp": "2024-04-21T10:45:38Z",
      "previous_timestamp": "2024-04-21T10:40:38Z",
      "next_timestamp": "2024-04-21T10:50:38Z",
      "data": {
        "id": "41a7ce09d7c82193024084293f2a8f9e",
        "sport_key": "cricket_ipl",
        "sport_title": "IPL",
        "commence_time": "2024-04-21T10:00:00Z",
        "home_team": "Kolkata Knight Riders",
        "away_team": "Royal Challengers Bangalore",
        "bookmakers": [
          {
            "key": "draftkings",
            "title": "DraftKings",
            "last_update": "2024-04-21T10:45:28Z",
            "markets": [
              {
                "key": "h2h",
                "last_update": "2024-04-21T10:45:28Z",
                "outcomes": [
                  {
                    "name": "Kolkata Knight Riders",
                    "price": 1.47
                  },
                  {
                    "name": "Royal Challengers Bangalore",
                    "price": 2.7
                  }
                ]
              }
            ]
          }
        ]
      }
    }
  },
  {
    "timestamp": "2024-04-21T10:55:00Z",
    "odds": {
      "timestamp": "2024-04-21T10:50:38Z",
      "previous_timestamp": "2024-04-21T10:45:38Z",
      "next_timestamp": "2024-04-21T10:55:38Z",
      "data": {
        "id": "41a7ce09d7c82193024084293f2a8f9e",
        "sport_key": "cricket_ipl",
        "sport_title": "IPL",
        "commence_time": "2024-04-21T10:00:00Z",
        "home_team": "Kolkata Knight Riders",
        "away_team": "Royal Challengers Bangalore",
        "bookmakers": [
          {
            "key": "draftkings",
            "title": "DraftKings",
            "last_update": "2024-04-21T10:49:46Z",
            "markets": [
              {
                "key": "h2h",
                "last_update": "2024-04-21T10:49:46Z",
                "outcomes": [
                  {
                    "name": "Kolkata Knight Riders",
                    "price": 1.36
                  },
                  {
                    "name": "Royal Challengers Bangalore",
                    "price": 3.15
                  }
                ]
              }
            ]
          }
        ]
      }
    }
  },
  {
    "timestamp": "2024-04-21T11:00:00Z",
    "odds": {
      "timestamp": "2024-04-21T10:55:38Z",
      "previous_timestamp": "2024-04-21T10:50:38Z",
      "next_timestamp": "2024-04-21T11:00:38Z",
      "data": {
        "id": "41a7ce09d7c82193024084293f2a8f9e",
        "sport_key": "cricket_ipl",
        "sport_title": "IPL",
        "commence_time": "2024-04-21T10:00:00Z",
        "home_team": "Kolkata Knight Riders",
        "away_team": "Royal Challengers Bangalore",
        "bookmakers": [
          {
            "key": "draftkings",
            "title": "DraftKings",
            "last_update": "2024-04-21T10:55:05Z",
            "markets": [
              {
                "key": "h2h",
                "last_update": "2024-04-21T10:55:05Z",
                "outcomes": [
                  {
                    "name": "Kolkata Knight Riders",
                    "price": 1.41
                  },
                  {
                    "name": "Royal Challengers Bangalore",
                    "price": 2.95
                  }
                ]
              }
            ]
          }
        ]
      }
    }
  },
  {
    "timestamp": "2024-04-21T11:05:00Z",
    "odds": {
      "timestamp": "2024-04-21T11:00:38Z",
      "previous_timestamp": "2024-04-21T10:55:38Z",
      "next_timestamp": "2024-04-21T11:05:39Z",
      "data": {
        "id": "41a7ce09d7c82193024084293f2a8f9e",
        "sport_key": "cricket_ipl",
        "sport_title": "IPL",
        "commence_time": "2024-04-21T10:00:00Z",
        "home_team": "Kolkata Knight Riders",
        "away_team": "Royal Challengers Bangalore",
        "bookmakers": [
          {
            "key": "draftkings",
            "title": "DraftKings",
            "last_update": "2024-04-21T11:00:27Z",
            "markets": [
              {
                "key": "h2h",
                "last_update": "2024-04-21T11:00:27Z",
                "outcomes": [
                  {
                    "name": "Kolkata Knight Riders",
                    "price": 1.43
                  },
                  {
                    "name": "Royal Challengers Bangalore",
                    "price": 2.85
                  }
                ]
              }
            ]
          }
        ]
      }
    }
  },
  {
    "timestamp": "2024-04-21T11:10:00Z",
    "odds": {
      "timestamp": "2024-04-21T11:05:39Z",
      "previous_timestamp": "2024-04-21T11:00:38Z",
      "next_timestamp": "2024-04-21T11:10:38Z",
      "data": {
        "id": "41a7ce09d7c82193024084293f2a8f9e",
        "sport_key": "cricket_ipl",
        "sport_title": "IPL",
        "commence_time": "2024-04-21T10:00:00Z",
        "home_team": "Kolkata Knight Riders",
        "away_team": "Royal Challengers Bangalore",
        "bookmakers": [
          {
            "key": "draftkings",
            "title": "DraftKings",
            "last_update": "2024-04-21T11:04:08Z",
            "markets": [
              {
                "key": "h2h",
                "last_update": "2024-04-21T11:04:08Z",
                "outcomes": [
                  {
                    "name": "Kolkata Knight Riders",
                    "price": 1.44
                  },
                  {
                    "name": "Royal Challengers Bangalore",
                    "price": 2.8
                  }
                ]
              }
            ]
          }
        ]
      }
    }
  },
  {
    "timestamp": "2024-04-21T11:15:00Z",
    "odds": {
      "timestamp": "2024-04-21T11:10:38Z",
      "previous_timestamp": "2024-04-21T11:05:39Z",
      "next_timestamp": "2024-04-21T11:15:38Z",
      "data": {
        "id": "41a7ce09d7c82193024084293f2a8f9e",
        "sport_key": "cricket_ipl",
        "sport_title": "IPL",
        "commence_time": "2024-04-21T10:00:00Z",
        "home_team": "Kolkata Knight Riders",
        "away_team": "Royal Challengers Bangalore",
        "bookmakers": [
          {
            "key": "draftkings",
            "title": "DraftKings",
            "last_update": "2024-04-21T11:09:25Z",
            "markets": [
              {
                "key": "h2h",
                "last_update": "2024-04-21T11:09:25Z",
                "outcomes": [
                  {
                    "name": "Kolkata Knight Riders",
                    "price": 1.41
                  },
                  {
                    "name": "Royal Challengers Bangalore",
                    "price": 2.9
                  }
                ]
              }
            ]
          }
        ]
      }
    }
  },
  {
    "timestamp": "2024-04-21T11:20:00Z",
    "odds": {
      "timestamp": "2024-04-21T11:15:38Z",
      "previous_timestamp": "2024-04-21T11:10:38Z",
      "next_timestamp": "2024-04-21T11:20:38Z",
      "data": {
        "id": "41a7ce09d7c82193024084293f2a8f9e",
        "sport_key": "cricket_ipl",
        "sport_title": "IPL",
        "commence_time": "2024-04-21T10:00:00Z",
        "home_team": "Kolkata Knight Riders",
        "away_team": "Royal Challengers Bangalore",
        "bookmakers": [
          {
            "key": "draftkings",
            "title": "DraftKings",
            "last_update": "2024-04-21T11:12:00Z",
            "markets": [
              {
                "key": "h2h",
                "last_update": "2024-04-21T11:12:00Z",
                "outcomes": [
                  {
                    "name": "Kolkata Knight Riders",
                    "price": 1.34
                  },
                  {
                    "name": "Royal Challengers Bangalore",
                    "price": 3.3
                  }
                ]
              }
            ]
          }
        ]
      }
    }
  },
  {
    "timestamp": "2024-04-21T11:25:00Z",
    "odds": {
      "timestamp": "2024-04-21T11:20:38Z",
      "previous_timestamp": "2024-04-21T11:15:38Z",
      "next_timestamp": "2024-04-21T11:25:38Z",
      "data": {
        "id": "41a7ce09d7c82193024084293f2a8f9e",
        "sport_key": "cricket_ipl",
        "sport_title": "IPL",
        "commence_time": "2024-04-21T10:00:00Z",
        "home_team": "Kolkata Knight Riders",
        "away_team": "Royal Challengers Bangalore",
        "bookmakers": [
          {
            "key": "draftkings",
            "title": "DraftKings",
            "last_update": "2024-04-21T11:19:45Z",
            "markets": [
              {
                "key": "h2h",
                "last_update": "2024-04-21T11:19:45Z",
                "outcomes": [
                  {
                    "name": "Kolkata Knight Riders",
                    "price": 1.49
                  },
                  {
                    "name": "Royal Challengers Bangalore",
                    "price": 2.6
                  }
                ]
              }
            ]
          }
        ]
      }
    }
  },
  {
    "timestamp": "2024-04-21T11:30:00Z",
    "odds": {
      "timestamp": "2024-04-21T11:25:38Z",
      "previous_timestamp": "2024-04-21T11:20:38Z",
      "next_timestamp": "2024-04-21T11:30:38Z",
      "data": {
        "id": "41a7ce09d7c82193024084293f2a8f9e",
        "sport_key": "cricket_ipl",
        "sport_title": "IPL",
        "commence_time": "2024-04-21T10:00:00Z",
        "home_team": "Kolkata Knight Riders",
        "away_team": "Royal Challengers Bangalore",
        "bookmakers": [
          {
            "key": "draftkings",
            "title": "DraftKings",
            "last_update": "2024-04-21T11:24:59Z",
            "markets": [
              {
                "key": "h2h",
                "last_update": "2024-04-21T11:24:59Z",
                "outcomes": [
                  {
                    "name": "Kolkata Knight Riders",
                    "price": 1.48
                  },
                  {
                    "name": "Royal Challengers Bangalore",
                    "price": 2.65
                  }
                ]
              }
            ]
          }
        ]
      }
    }
  },
  {
    "timestamp": "2024-04-21T11:35:00Z",
    "odds": {
      "timestamp": "2024-04-21T11:30:38Z",
      "previous_timestamp": "2024-04-21T11:25:38Z",
      "next_timestamp": "2024-04-21T11:35:38Z",
      "data": {
        "id": "41a7ce09d7c82193024084293f2a8f9e",
        "sport_key": "cricket_ipl",
        "sport_title": "IPL",
        "commence_time": "2024-04-21T10:00:00Z",
        "home_team": "Kolkata Knight Riders",
        "away_team": "Royal Challengers Bangalore",
        "bookmakers": [
          {
            "key": "draftkings",
            "title": "DraftKings",
            "last_update": "2024-04-21T11:30:14Z",
            "markets": [
              {
                "key": "h2h",
                "last_update": "2024-04-21T11:30:14Z",
                "outcomes": [
                  {
                    "name": "Kolkata Knight Riders",
                    "price": 1.49
                  },
                  {
                    "name": "Royal Challengers Bangalore",
                    "price": 2.6
                  }
                ]
              }
            ]
          }
        ]
      }
    }
  },
  {
    "timestamp": "2024-04-21T11:40:00Z",
    "odds": {
      "timestamp": "2024-04-21T11:35:38Z",
      "previous_timestamp": "2024-04-21T11:30:38Z",
      "next_timestamp": "2024-04-21T11:40:38Z",
      "data": {
        "id": "41a7ce09d7c82193024084293f2a8f9e",
        "sport_key": "cricket_ipl",
        "sport_title": "IPL",
        "commence_time": "2024-04-21T10:00:00Z",
        "home_team": "Kolkata Knight Riders",
        "away_team": "Royal Challengers Bangalore",
        "bookmakers": [
          {
            "key": "draftkings",
            "title": "DraftKings",
            "last_update": "2024-04-21T11:35:30Z",
            "markets": [
              {
                "key": "h2h",
                "last_update": "2024-04-21T11:35:30Z",
                "outcomes": [
                  {
                    "name": "Kolkata Knight Riders",
                    "price": 1.38
                  },
                  {
                    "name": "Royal Challengers Bangalore",
                    "price": 3.1
                  }
                ]
              }
            ]
          }
        ]
      }
    }
  },
  {
    "timestamp": "2024-04-21T11:45:00Z",
    "odds": {
      "timestamp": "2024-04-21T11:40:38Z",
      "previous_timestamp": "2024-04-21T11:35:38Z",
      "next_timestamp": "2024-04-21T11:45:38Z",
      "data": {
        "id": "41a7ce09d7c82193024084293f2a8f9e",
        "sport_key": "cricket_ipl",
        "sport_title": "IPL",
        "commence_time": "2024-04-21T10:00:00Z",
        "home_team": "Kolkata Knight Riders",
        "away_team": "Royal Challengers Bangalore",
        "bookmakers": [
          {
            "key": "draftkings",
            "title": "DraftKings",
            "last_update": "2024-04-21T11:39:47Z",
            "markets": [
              {
                "key": "h2h",
                "last_update": "2024-04-21T11:39:47Z",
                "outcomes": [
                  {
                    "name": "Kolkata Knight Riders",
                    "price": 1.31
                  },
                  {
                    "name": "Royal Challengers Bangalore",
                    "price": 3.55
                  }
                ]
              }
            ]
          }
        ]
      }
    }
  },
  {
    "timestamp": "2024-04-21T11:50:00Z",
    "odds": {
      "timestamp": "2024-04-21T11:45:38Z",
      "previous_timestamp": "2024-04-21T11:40:38Z",
      "next_timestamp": "2024-04-21T11:50:38Z",
      "data": {
        "id": "41a7ce09d7c82193024084293f2a8f9e",
        "sport_key": "cricket_ipl",
        "sport_title": "IPL",
        "commence_time": "2024-04-21T10:00:00Z",
        "home_team": "Kolkata Knight Riders",
        "away_team": "Royal Challengers Bangalore",
        "bookmakers": [
          {
            "key": "draftkings",
            "title": "DraftKings",
            "last_update": "2024-04-21T11:45:08Z",
            "markets": [
              {
                "key": "h2h",
                "last_update": "2024-04-21T11:45:08Z",
                "outcomes": [
                  {
                    "name": "Kolkata Knight Riders",
                    "price": 1.32
                  },
                  {
                    "name": "Royal Challengers Bangalore",
                    "price": 3.4
                  }
                ]
              }
            ]
          }
        ]
      }
    }
  },
  {
    "timestamp": "2024-04-21T11:55:00Z",
    "odds": {
      "timestamp": "2024-04-21T11:50:38Z",
      "previous_timestamp": "2024-04-21T11:45:38Z",
      "next_timestamp": "2024-04-21T11:55:38Z",
      "data": {
        "id": "41a7ce09d7c82193024084293f2a8f9e",
        "sport_key": "cricket_ipl",
        "sport_title": "IPL",
        "commence_time": "2024-04-21T10:00:00Z",
        "home_team": "Kolkata Knight Riders",
        "away_team": "Royal Challengers Bangalore",
        "bookmakers": [
          {
            "key": "draftkings",
            "title": "DraftKings",
            "last_update": "2024-04-21T11:48:58Z",
            "markets": [
              {
                "key": "h2h",
                "last_update": "2024-04-21T11:48:58Z",
                "outcomes": [
                  {
                    "name": "Kolkata Knight Riders",
                    "price": 1.28
                  },
                  {
                    "name": "Royal Challengers Bangalore",
                    "price": 3.85
                  }
                ]
              }
            ]
          }
        ]
      }
    }
  },
  {
    "timestamp": "2024-04-21T12:00:00Z",
    "odds": {
      "timestamp": "2024-04-21T11:55:38Z",
      "previous_timestamp": "2024-04-21T11:50:38Z",
      "next_timestamp": "2024-04-21T12:00:39Z",
      "data": {
        "id": "41a7ce09d7c82193024084293f2a8f9e",
        "sport_key": "cricket_ipl",
        "sport_title": "IPL",
        "commence_time": "2024-04-21T10:00:00Z",
        "home_team": "Kolkata Knight Riders",
        "away_team": "Royal Challengers Bangalore",
        "bookmakers": [
          {
            "key": "draftkings",
            "title": "DraftKings",
            "last_update": "2024-04-21T11:54:19Z",
            "markets": [
              {
                "key": "h2h",
                "last_update": "2024-04-21T11:54:19Z",
                "outcomes": [
                  {
                    "name": "Kolkata Knight Riders",
                    "price": 1.29
                  },
                  {
                    "name": "Royal Challengers Bangalore",
                    "price": 3.65
                  }
                ]
              }
            ]
          }
        ]
      }
    }
  },
  {
    "timestamp": "2024-04-21T12:05:00Z",
    "odds": {
      "timestamp": "2024-04-21T12:00:39Z",
      "previous_timestamp": "2024-04-21T11:55:38Z",
      "next_timestamp": "2024-04-21T12:05:38Z",
      "data": {
        "id": "41a7ce09d7c82193024084293f2a8f9e",
        "sport_key": "cricket_ipl",
        "sport_title": "IPL",
        "commence_time": "2024-04-21T10:00:00Z",
        "home_team": "Kolkata Knight Riders",
        "away_team": "Royal Challengers Bangalore",
        "bookmakers": [
          {
            "key": "draftkings",
            "title": "DraftKings",
            "last_update": "2024-04-21T11:58:32Z",
            "markets": [
              {
                "key": "h2h",
                "last_update": "2024-04-21T11:58:32Z",
                "outcomes": [
                  {
                    "name": "Kolkata Knight Riders",
                    "price": 1.28
                  },
                  {
                    "name": "Royal Challengers Bangalore",
                    "price": 3.7
                  }
                ]
              }
            ]
          }
        ]
      }
    }
  },
  {
    "timestamp": "2024-04-21T12:10:00Z",
    "odds": {
      "timestamp": "2024-04-21T12:05:38Z",
      "previous_timestamp": "2024-04-21T12:00:39Z",
      "next_timestamp": "2024-04-21T12:10:38Z",
      "data": {
        "id": "41a7ce09d7c82193024084293f2a8f9e",
        "sport_key": "cricket_ipl",
        "sport_title": "IPL",
        "commence_time": "2024-04-21T10:00:00Z",
        "home_team": "Kolkata Knight Riders",
        "away_team": "Royal Challengers Bangalore",
        "bookmakers": [
          {
            "key": "draftkings",
            "title": "DraftKings",
            "last_update": "2024-04-21T12:05:06Z",
            "markets": [
              {
                "key": "h2h",
                "last_update": "2024-04-21T12:05:06Z",
                "outcomes": [
                  {
                    "name": "Kolkata Knight Riders",
                    "price": 1.26
                  },
                  {
                    "name": "Royal Challengers Bangalore",
                    "price": 3.95
                  }
                ]
              }
            ]
          }
        ]
      }
    }
  },
  {
    "timestamp": "2024-04-21T12:15:00Z",
    "odds": {
      "timestamp": "2024-04-21T12:10:38Z",
      "previous_timestamp": "2024-04-21T12:05:38Z",
      "next_timestamp": "2024-04-21T12:15:39Z",
      "data": {
        "id": "41a7ce09d7c82193024084293f2a8f9e",
        "sport_key": "cricket_ipl",
        "sport_title": "IPL",
        "commence_time": "2024-04-21T10:00:00Z",
        "home_team": "Kolkata Knight Riders",
        "away_team": "Royal Challengers Bangalore",
        "bookmakers": [
          {
            "key": "draftkings",
            "title": "DraftKings",
            "last_update": "2024-04-21T12:10:30Z",
            "markets": [
              {
                "key": "h2h",
                "last_update": "2024-04-21T12:10:30Z",
                "outcomes": [
                  {
                    "name": "Kolkata Knight Riders",
                    "price": 1.28
                  },
                  {
                    "name": "Royal Challengers Bangalore",
                    "price": 3.7
                  }
                ]
              }
            ]
          }
        ]
      }
    }
  },
  {
    "timestamp": "2024-04-21T12:20:00Z",
    "odds": {
      "timestamp": "2024-04-21T12:15:39Z",
      "previous_timestamp": "2024-04-21T12:10:38Z",
      "next_timestamp": "2024-04-21T12:20:38Z",
      "data": {
        "id": "41a7ce09d7c82193024084293f2a8f9e",
        "sport_key": "cricket_ipl",
        "sport_title": "IPL",
        "commence_time": "2024-04-21T10:00:00Z",
        "home_team": "Kolkata Knight Riders",
        "away_team": "Royal Challengers Bangalore",
        "bookmakers": [
          {
            "key": "draftkings",
            "title": "DraftKings",
            "last_update": "2024-04-21T12:14:41Z",
            "markets": [
              {
                "key": "h2h",
                "last_update": "2024-04-21T12:14:41Z",
                "outcomes": [
                  {
                    "name": "Kolkata Knight Riders",
                    "price": 1.31
                  },
                  {
                    "name": "Royal Challengers Bangalore",
                    "price": 3.4
                  }
                ]
              }
            ]
          }
        ]
      }
    }
  },
  {
    "timestamp": "2024-04-21T12:25:00Z",
    "odds": {
      "timestamp": "2024-04-21T12:20:38Z",
      "previous_timestamp": "2024-04-21T12:15:39Z",
      "next_timestamp": "2024-04-21T12:25:38Z",
      "data": {
        "id": "41a7ce09d7c82193024084293f2a8f9e",
        "sport_key": "cricket_ipl",
        "sport_title": "IPL",
        "commence_time": "2024-04-21T10:00:00Z",
        "home_team": "Kolkata Knight Riders",
        "away_team": "Royal Challengers Bangalore",
        "bookmakers": [
          {
            "key": "draftkings",
            "title": "DraftKings",
            "last_update": "2024-04-21T12:15:51Z",
            "markets": [
              {
                "key": "h2h",
                "last_update": "2024-04-21T12:15:51Z",
                "outcomes": [
                  {
                    "name": "Kolkata Knight Riders",
                    "price": 1.38
                  },
                  {
                    "name": "Royal Challengers Bangalore",
                    "price": 3.0
                  }
                ]
              }
            ]
          }
        ]
      }
    }
  },
  {
    "timestamp": "2024-04-21T12:30:00Z",
    "odds": {
      "timestamp": "2024-04-21T12:25:38Z",
      "previous_timestamp": "2024-04-21T12:20:38Z",
      "next_timestamp": "2024-04-21T12:30:38Z",
      "data": {
        "id": "41a7ce09d7c82193024084293f2a8f9e",
        "sport_key": "cricket_ipl",
        "sport_title": "IPL",
        "commence_time": "2024-04-21T10:00:00Z",
        "home_team": "Kolkata Knight Riders",
        "away_team": "Royal Challengers Bangalore",
        "bookmakers": [
          {
            "key": "draftkings",
            "title": "DraftKings",
            "last_update": "2024-04-21T12:22:54Z",
            "markets": [
              {
                "key": "h2h",
                "last_update": "2024-04-21T12:22:54Z",
                "outcomes": [
                  {
                    "name": "Kolkata Knight Riders",
                    "price": 1.54
                  },
                  {
                    "name": "Royal Challengers Bangalore",
                    "price": 2.35
                  }
                ]
              }
            ]
          }
        ]
      }
    }
  },
  {
    "timestamp": "2024-04-21T12:35:00Z",
    "odds": {
      "timestamp": "2024-04-21T12:30:38Z",
      "previous_timestamp": "2024-04-21T12:25:38Z",
      "next_timestamp": "2024-04-21T12:35:38Z",
      "data": {
        "id": "41a7ce09d7c82193024084293f2a8f9e",
        "sport_key": "cricket_ipl",
        "sport_title": "IPL",
        "commence_time": "2024-04-21T10:00:00Z",
        "home_team": "Kolkata Knight Riders",
        "away_team": "Royal Challengers Bangalore",
        "bookmakers": [
          {
            "key": "draftkings",
            "title": "DraftKings",
            "last_update": "2024-04-21T12:22:54Z",
            "markets": [
              {
                "key": "h2h",
                "last_update": "2024-04-21T12:22:54Z",
                "outcomes": [
                  {
                    "name": "Kolkata Knight Riders",
                    "price": 1.54
                  },
                  {
                    "name": "Royal Challengers Bangalore",
                    "price": 2.35
                  }
                ]
              }
            ]
          }
        ]
      }
    }
  },
  {
    "timestamp": "2024-04-21T12:40:00Z",
    "odds": {
      "timestamp": "2024-04-21T12:35:38Z",
      "previous_timestamp": "2024-04-21T12:30:38Z",
      "next_timestamp": "2024-04-21T12:40:39Z",
      "data": {
        "id": "41a7ce09d7c82193024084293f2a8f9e",
        "sport_key": "cricket_ipl",
        "sport_title": "IPL",
        "commence_time": "2024-04-21T10:00:00Z",
        "home_team": "Kolkata Knight Riders",
        "away_team": "Royal Challengers Bangalore",
        "bookmakers": [
          {
            "key": "draftkings",
            "title": "DraftKings",
            "last_update": "2024-04-21T12:35:02Z",
            "markets": [
              {
                "key": "h2h",
                "last_update": "2024-04-21T12:35:02Z",
                "outcomes": [
                  {
                    "name": "Kolkata Knight Riders",
                    "price": 1.32
                  },
                  {
                    "name": "Royal Challengers Bangalore",
                    "price": 3.5
                  }
                ]
              }
            ]
          }
        ]
      }
    }
  },
  {
    "timestamp": "2024-04-21T12:45:00Z",
    "odds": {
      "timestamp": "2024-04-21T12:40:39Z",
      "previous_timestamp": "2024-04-21T12:35:38Z",
      "next_timestamp": "2024-04-21T12:45:38Z",
      "data": {
        "id": "41a7ce09d7c82193024084293f2a8f9e",
        "sport_key": "cricket_ipl",
        "sport_title": "IPL",
        "commence_time": "2024-04-21T10:00:00Z",
        "home_team": "Kolkata Knight Riders",
        "away_team": "Royal Challengers Bangalore",
        "bookmakers": [
          {
            "key": "draftkings",
            "title": "DraftKings",
            "last_update": "2024-04-21T12:40:29Z",
            "markets": [
              {
                "key": "h2h",
                "last_update": "2024-04-21T12:40:29Z",
                "outcomes": [
                  {
                    "name": "Kolkata Knight Riders",
                    "price": 1.22
                  },
                  {
                    "name": "Royal Challengers Bangalore",
                    "price": 4.5
                  }
                ]
              }
            ]
          }
        ]
      }
    }
  },
  {
    "timestamp": "2024-04-21T12:50:00Z",
    "odds": {
      "timestamp": "2024-04-21T12:45:38Z",
      "previous_timestamp": "2024-04-21T12:40:39Z",
      "next_timestamp": "2024-04-21T12:50:39Z",
      "data": {
        "id": "41a7ce09d7c82193024084293f2a8f9e",
        "sport_key": "cricket_ipl",
        "sport_title": "IPL",
        "commence_time": "2024-04-21T10:00:00Z",
        "home_team": "Kolkata Knight Riders",
        "away_team": "Royal Challengers Bangalore",
        "bookmakers": [
          {
            "key": "draftkings",
            "title": "DraftKings",
            "last_update": "2024-04-21T12:44:52Z",
            "markets": [
              {
                "key": "h2h",
                "last_update": "2024-04-21T12:44:52Z",
                "outcomes": [
                  {
                    "name": "Kolkata Knight Riders",
                    "price": 1.38
                  },
                  {
                    "name": "Royal Challengers Bangalore",
                    "price": 3.05
                  }
                ]
              }
            ]
          }
        ]
      }
    }
  },
  {
    "timestamp": "2024-04-21T12:55:00Z",
    "odds": {
      "timestamp": "2024-04-21T12:50:39Z",
      "previous_timestamp": "2024-04-21T12:45:38Z",
      "next_timestamp": "2024-04-21T12:55:38Z",
      "data": {
        "id": "41a7ce09d7c82193024084293f2a8f9e",
        "sport_key": "cricket_ipl",
        "sport_title": "IPL",
        "commence_time": "2024-04-21T10:00:00Z",
        "home_team": "Kolkata Knight Riders",
        "away_team": "Royal Challengers Bangalore",
        "bookmakers": [
          {
            "key": "draftkings",
            "title": "DraftKings",
            "last_update": "2024-04-21T12:50:18Z",
            "markets": [
              {
                "key": "h2h",
                "last_update": "2024-04-21T12:50:18Z",
                "outcomes": [
                  {
                    "name": "Kolkata Knight Riders",
                    "price": 1.45
                  },
                  {
                    "name": "Royal Challengers Bangalore",
                    "price": 2.75
                  }
                ]
              }
            ]
          }
        ]
      }
    }
  },
  {
    "timestamp": "2024-04-21T13:00:00Z",
    "odds": {
      "timestamp": "2024-04-21T12:55:38Z",
      "previous_timestamp": "2024-04-21T12:50:39Z",
      "next_timestamp": "2024-04-21T13:00:38Z",
      "data": {
        "id": "41a7ce09d7c82193024084293f2a8f9e",
        "sport_key": "cricket_ipl",
        "sport_title": "IPL",
        "commence_time": "2024-04-21T10:00:00Z",
        "home_team": "Kolkata Knight Riders",
        "away_team": "Royal Challengers Bangalore",
        "bookmakers": [
          {
            "key": "draftkings",
            "title": "DraftKings",
            "last_update": "2024-04-21T12:54:05Z",
            "markets": [
              {
                "key": "h2h",
                "last_update": "2024-04-21T12:54:05Z",
                "outcomes": [
                  {
                    "name": "Kolkata Knight Riders",
                    "price": 1.38
                  },
                  {
                    "name": "Royal Challengers Bangalore",
                    "price": 3.05
                  }
                ]
              }
            ]
          }
        ]
      }
    }
  },
  {
    "timestamp": "2024-04-21T13:05:00Z",
    "odds": {
      "timestamp": "2024-04-21T13:00:38Z",
      "previous_timestamp": "2024-04-21T12:55:38Z",
      "next_timestamp": "2024-04-21T13:05:38Z",
      "data": {
        "id": "41a7ce09d7c82193024084293f2a8f9e",
        "sport_key": "cricket_ipl",
        "sport_title": "IPL",
        "commence_time": "2024-04-21T10:00:00Z",
        "home_team": "Kolkata Knight Riders",
        "away_team": "Royal Challengers Bangalore",
        "bookmakers": [
          {
            "key": "draftkings",
            "title": "DraftKings",
            "last_update": "2024-04-21T12:59:37Z",
            "markets": [
              {
                "key": "h2h",
                "last_update": "2024-04-21T12:59:37Z",
                "outcomes": [
                  {
                    "name": "Kolkata Knight Riders",
                    "price": 1.45
                  },
                  {
                    "name": "Royal Challengers Bangalore",
                    "price": 2.75
                  }
                ]
              }
            ]
          }
        ]
      }
    }
  },
  {
    "timestamp": "2024-04-21T13:10:00Z",
    "odds": {
      "timestamp": "2024-04-21T13:05:38Z",
      "previous_timestamp": "2024-04-21T13:00:38Z",
      "next_timestamp": "2024-04-21T13:10:38Z",
      "data": {
        "id": "41a7ce09d7c82193024084293f2a8f9e",
        "sport_key": "cricket_ipl",
        "sport_title": "IPL",
        "commence_time": "2024-04-21T10:00:00Z",
        "home_team": "Kolkata Knight Riders",
        "away_team": "Royal Challengers Bangalore",
        "bookmakers": [
          {
            "key": "draftkings",
            "title": "DraftKings",
            "last_update": "2024-04-21T13:04:59Z",
            "markets": [
              {
                "key": "h2h",
                "last_update": "2024-04-21T13:04:59Z",
                "outcomes": [
                  {
                    "name": "Kolkata Knight Riders",
                    "price": 1.95
                  },
                  {
                    "name": "Royal Challengers Bangalore",
                    "price": 1.8
                  }
                ]
              }
            ]
          }
        ]
      }
    }
  },
  {
    "timestamp": "2024-04-21T13:15:00Z",
    "odds": {
      "timestamp": "2024-04-21T13:10:38Z",
      "previous_timestamp": "2024-04-21T13:05:38Z",
      "next_timestamp": "2024-04-21T13:15:38Z",
      "data": {
        "id": "41a7ce09d7c82193024084293f2a8f9e",
        "sport_key": "cricket_ipl",
        "sport_title": "IPL",
        "commence_time": "2024-04-21T10:00:00Z",
        "home_team": "Kolkata Knight Riders",
        "away_team": "Royal Challengers Bangalore",
        "bookmakers": [
          {
            "key": "draftkings",
            "title": "DraftKings",
            "last_update": "2024-04-21T13:10:28Z",
            "markets": [
              {
                "key": "h2h",
                "last_update": "2024-04-21T13:10:28Z",
                "outcomes": [
                  {
                    "name": "Kolkata Knight Riders",
                    "price": 3.2
                  },
                  {
                    "name": "Royal Challengers Bangalore",
                    "price": 1.35
                  }
                ]
              }
            ]
          }
        ]
      }
    }
  },
  {
    "timestamp": "2024-04-21T13:20:00Z",
    "odds": {
      "timestamp": "2024-04-21T13:15:38Z",
      "previous_timestamp": "2024-04-21T13:10:38Z",
      "next_timestamp": "2024-04-21T13:20:38Z",
      "data": {
        "id": "41a7ce09d7c82193024084293f2a8f9e",
        "sport_key": "cricket_ipl",
        "sport_title": "IPL",
        "commence_time": "2024-04-21T10:00:00Z",
        "home_team": "Kolkata Knight Riders",
        "away_team": "Royal Challengers Bangalore",
        "bookmakers": [
          {
            "key": "draftkings",
            "title": "DraftKings",
            "last_update": "2024-04-21T13:10:28Z",
            "markets": [
              {
                "key": "h2h",
                "last_update": "2024-04-21T13:10:28Z",
                "outcomes": [
                  {
                    "name": "Kolkata Knight Riders",
                    "price": 3.2
                  },
                  {
                    "name": "Royal Challengers Bangalore",
                    "price": 1.35
                  }
                ]
              }
            ]
          }
        ]
      }
    }
  },
  {
    "timestamp": "2024-04-21T13:25:00Z",
    "odds": {
      "timestamp": "2024-04-21T13:20:38Z",
      "previous_timestamp": "2024-04-21T13:15:38Z",
      "next_timestamp": "2024-04-21T13:25:38Z",
      "data": {
        "id": "41a7ce09d7c82193024084293f2a8f9e",
        "sport_key": "cricket_ipl",
        "sport_title": "IPL",
        "commence_time": "2024-04-21T10:00:00Z",
        "home_team": "Kolkata Knight Riders",
        "away_team": "Royal Challengers Bangalore",
        "bookmakers": [
          {
            "key": "draftkings",
            "title": "DraftKings",
            "last_update": "2024-04-21T13:18:38Z",
            "markets": [
              {
                "key": "h2h",
                "last_update": "2024-04-21T13:18:38Z",
                "outcomes": [
                  {
                    "name": "Kolkata Knight Riders",
                    "price": 2.1
                  },
                  {
                    "name": "Royal Challengers Bangalore",
                    "price": 1.74
                  }
                ]
              }
            ]
          }
        ]
      }
    }
  },
  {
    "timestamp": "2024-04-21T13:30:00Z",
    "odds": {
      "timestamp": "2024-04-21T13:25:38Z",
      "previous_timestamp": "2024-04-21T13:20:38Z",
      "next_timestamp": "2024-04-21T13:30:38Z",
      "data": {
        "id": "41a7ce09d7c82193024084293f2a8f9e",
        "sport_key": "cricket_ipl",
        "sport_title": "IPL",
        "commence_time": "2024-04-21T10:00:00Z",
        "home_team": "Kolkata Knight Riders",
        "away_team": "Royal Challengers Bangalore",
        "bookmakers": [
          {
            "key": "draftkings",
            "title": "DraftKings",
            "last_update": "2024-04-21T13:24:19Z",
            "markets": [
              {
                "key": "h2h",
                "last_update": "2024-04-21T13:24:19Z",
                "outcomes": [
                  {
                    "name": "Kolkata Knight Riders",
                    "price": 1.61
                  },
                  {
                    "name": "Royal Challengers Bangalore",
                    "price": 2.3
                  }
                ]
              }
            ]
          }
        ]
      }
    }
  },
  {
    "timestamp": "2024-04-21T13:35:00Z",
    "odds": {
      "timestamp": "2024-04-21T13:30:38Z",
      "previous_timestamp": "2024-04-21T13:25:38Z",
      "next_timestamp": "2024-04-21T13:35:39Z",
      "data": {
        "id": "41a7ce09d7c82193024084293f2a8f9e",
        "sport_key": "cricket_ipl",
        "sport_title": "IPL",
        "commence_time": "2024-04-21T10:00:00Z",
        "home_team": "Kolkata Knight Riders",
        "away_team": "Royal Challengers Bangalore",
        "bookmakers": [
          {
            "key": "draftkings",
            "title": "DraftKings",
            "last_update": "2024-04-21T13:29:57Z",
            "markets": [
              {
                "key": "h2h",
                "last_update": "2024-04-21T13:29:57Z",
                "outcomes": [
                  {
                    "name": "Kolkata Knight Riders",
                    "price": 2.1
                  },
                  {
                    "name": "Royal Challengers Bangalore",
                    "price": 1.71
                  }
                ]
              }
            ]
          }
        ]
      }
    }
  },
  {
    "timestamp": "2024-04-21T13:40:00Z",
    "odds": {
      "timestamp": "2024-04-21T13:35:39Z",
      "previous_timestamp": "2024-04-21T13:30:38Z",
      "next_timestamp": "2024-04-21T13:40:38Z",
      "data": {
        "id": "41a7ce09d7c82193024084293f2a8f9e",
        "sport_key": "cricket_ipl",
        "sport_title": "IPL",
        "commence_time": "2024-04-21T10:00:00Z",
        "home_team": "Kolkata Knight Riders",
        "away_team": "Royal Challengers Bangalore",
        "bookmakers": [
          {
            "key": "draftkings",
            "title": "DraftKings",
            "last_update": "2024-04-21T13:34:26Z",
            "markets": [
              {
                "key": "h2h",
                "last_update": "2024-04-21T13:34:26Z",
                "outcomes": [
                  {
                    "name": "Kolkata Knight Riders",
                    "price": 2.1
                  },
                  {
                    "name": "Royal Challengers Bangalore",
                    "price": 1.74
                  }
                ]
              }
            ]
          }
        ]
      }
    }
  },
  {
    "timestamp": "2024-04-21T13:45:00Z",
    "odds": {
      "timestamp": "2024-04-21T13:40:38Z",
      "previous_timestamp": "2024-04-21T13:35:39Z",
      "next_timestamp": "2024-04-21T13:45:39Z",
      "data": {
        "id": "41a7ce09d7c82193024084293f2a8f9e",
        "sport_key": "cricket_ipl",
        "sport_title": "IPL",
        "commence_time": "2024-04-21T10:00:00Z",
        "home_team": "Kolkata Knight Riders",
        "away_team": "Royal Challengers Bangalore",
        "bookmakers": [
          {
            "key": "draftkings",
            "title": "DraftKings",
            "last_update": "2024-04-21T13:40:09Z",
            "markets": [
              {
                "key": "h2h",
                "last_update": "2024-04-21T13:40:09Z",
                "outcomes": [
                  {
                    "name": "Kolkata Knight Riders",
                    "price": 2.2
                  },
                  {
                    "name": "Royal Challengers Bangalore",
                    "price": 1.67
                  }
                ]
              }
            ]
          }
        ]
      }
    }
  },
  {
    "timestamp": "2024-04-21T13:50:00Z",
    "odds": {
      "timestamp": "2024-04-21T13:45:39Z",
      "previous_timestamp": "2024-04-21T13:40:38Z",
      "next_timestamp": "2024-04-21T13:50:38Z",
      "data": {
        "id": "41a7ce09d7c82193024084293f2a8f9e",
        "sport_key": "cricket_ipl",
        "sport_title": "IPL",
        "commence_time": "2024-04-21T10:00:00Z",
        "home_team": "Kolkata Knight Riders",
        "away_team": "Royal Challengers Bangalore",
        "bookmakers": [
          {
            "key": "draftkings",
            "title": "DraftKings",
            "last_update": "2024-04-21T13:44:11Z",
            "markets": [
              {
                "key": "h2h",
                "last_update": "2024-04-21T13:44:11Z",
                "outcomes": [
                  {
                    "name": "Kolkata Knight Riders",
                    "price": 1.87
                  },
                  {
                    "name": "Royal Challengers Bangalore",
                    "price": 1.91
                  }
                ]
              }
            ]
          }
        ]
      }
    }
  },
  {
    "timestamp": "2024-04-21T13:55:00Z",
    "odds": {
      "timestamp": "2024-04-21T13:50:38Z",
      "previous_timestamp": "2024-04-21T13:45:39Z",
      "next_timestamp": "2024-04-21T13:55:38Z",
      "data": {
        "id": "41a7ce09d7c82193024084293f2a8f9e",
        "sport_key": "cricket_ipl",
        "sport_title": "IPL",
        "commence_time": "2024-04-21T10:00:00Z",
        "home_team": "Kolkata Knight Riders",
        "away_team": "Royal Challengers Bangalore",
        "bookmakers": [
          {
            "key": "draftkings",
            "title": "DraftKings",
            "last_update": "2024-04-21T13:49:51Z",
            "markets": [
              {
                "key": "h2h",
                "last_update": "2024-04-21T13:49:51Z",
                "outcomes": [
                  {
                    "name": "Kolkata Knight Riders",
                    "price": 1.34
                  },
                  {
                    "name": "Royal Challengers Bangalore",
                    "price": 3.25
                  }
                ]
              }
            ]
          }
        ]
      }
    }
  },
  {
    "timestamp": "2024-04-21T14:00:00Z",
    "odds": {
      "timestamp": "2024-04-21T13:55:38Z",
      "previous_timestamp": "2024-04-21T13:50:38Z",
      "next_timestamp": "2024-04-21T14:00:39Z",
      "data": {
        "id": "41a7ce09d7c82193024084293f2a8f9e",
        "sport_key": "cricket_ipl",
        "sport_title": "IPL",
        "commence_time": "2024-04-21T10:00:00Z",
        "home_team": "Kolkata Knight Riders",
        "away_team": "Royal Challengers Bangalore",
        "bookmakers": [
          {
            "key": "draftkings",
            "title": "DraftKings",
            "last_update": "2024-04-21T13:54:17Z",
            "markets": [
              {
                "key": "h2h",
                "last_update": "2024-04-21T13:54:17Z",
                "outcomes": [
                  {
                    "name": "Kolkata Knight Riders",
                    "price": 1.35
                  },
                  {
                    "name": "Royal Challengers Bangalore",
                    "price": 3.2
                  }
                ]
              }
            ]
          }
        ]
      }
    }
  },
  {
    "timestamp": "2024-04-21T14:05:00Z",
    "odds": {
      "timestamp": "2024-04-21T14:00:39Z",
      "previous_timestamp": "2024-04-21T13:55:38Z",
      "next_timestamp": "2024-04-21T14:05:38Z",
      "data": {
        "id": "41a7ce09d7c82193024084293f2a8f9e",
        "sport_key": "cricket_ipl",
        "sport_title": "IPL",
        "commence_time": "2024-04-21T10:00:00Z",
        "home_team": "Kolkata Knight Riders",
        "away_team": "Royal Challengers Bangalore",
        "bookmakers": [
          {
            "key": "draftkings",
            "title": "DraftKings",
            "last_update": "2024-04-21T13:57:26Z",
            "markets": [
              {
                "key": "h2h",
                "last_update": "2024-04-21T13:57:26Z",
                "outcomes": [
                  {
                    "name": "Kolkata Knight Riders",
                    "price": 1.43
                  },
                  {
                    "name": "Royal Challengers Bangalore",
                    "price": 2.85
                  }
                ]
              }
            ]
          }
        ]
      }
    }
  },
  {
    "timestamp": "2024-04-21T14:10:00Z",
    "odds": {
      "timestamp": "2024-04-21T14:05:38Z",
      "previous_timestamp": "2024-04-21T14:00:39Z",
      "next_timestamp": "2024-04-21T14:10:38Z",
      "data": {
        "id": "41a7ce09d7c82193024084293f2a8f9e",
        "sport_key": "cricket_ipl",
        "sport_title": "IPL",
        "commence_time": "2024-04-21T10:00:00Z",
        "home_team": "Kolkata Knight Riders",
        "away_team": "Royal Challengers Bangalore",
        "bookmakers": [
          {
            "key": "draftkings",
            "title": "DraftKings",
            "last_update": "2024-04-21T14:01:29Z",
            "markets": [
              {
                "key": "h2h",
                "last_update": "2024-04-21T14:01:29Z",
                "outcomes": [
                  {
                    "name": "Kolkata Knight Riders",
                    "price": 1.06
                  },
                  {
                    "name": "Royal Challengers Bangalore",
                    "price": 9.5
                  }
                ]
              }
            ]
          }
        ]
      }
    }
  }
]